README.md
setup.cfg
setup.py
mycelium/load.py
mycelium.egg-info/PKG-INFO
mycelium.egg-info/SOURCES.txt
mycelium.egg-info/dependency_links.txt
mycelium.egg-info/requires.txt
mycelium.egg-info/top_level.txt