Metadata-Version: 1.1
Name: mycelium
Version: 0.4.9
Summary: Library for writing dynamic, flexible workflows using python and luigi
Home-page: http://github.com/greenbyte/mycelium/
Author: Thomas Winter, Edmund Hood Highcock, Niklas Renström, Pramod Bangalore
Author-email: thomas@greenbyte.com
License: MIT
Download-URL: http://github.com/greenbyte/mycelium/archive/0.4.5.tar.gz
Keywords: workflow,pipeline,luigi,data science
Platform: UNKNOWN
